[
  {
    "source_id": "1047442",
    "title": "Robot Học Tiếng Anh Pika - PK-01 - Kèm Gói Phần Mềm Pika 6 Tháng",
    "slug": "robot-hoc-tieng-anh-pika-pk-01-kem-goi-phan-mem-pika-6-thang",
    "price": 3420000,
    "original_price": 3420000,
    "discount_percent": 0,
    "description_html": null,
    "image_url": "https://cdn1.fahasa.com/media/catalog/product/1/-/1-910x1024_1.jpg",
    "source_url": "https://www.fahasa.com/robot-hoc-tieng-anh-pika-pk-01-kem-goi-phan-mem-pika-6-thang.html",
    "label": null,
    "episode": null,
    "stock_status": "in_stock",
    "reviews_count": null,
    "rating_value": null,
    "category": "Đồ chơi - Lưu niệm"
  },
  {
    "source_id": "1053083",
    "title": "Blindbox Đồ Chơi Lắp Ráp Model Kit Moshow Version 1 - Sembo 900043",
    "slug": "blindbox-do-choi-lap-rap-model-kit-moshow-version-1-sembo-900043",
    "price": 54000,
    "original_price": 60000,
    "discount_percent": 10,
    "description_html": null,
    "image_url": "https://cdn1.fahasa.com/media/catalog/product/6/9/6941827014488.jpg",
    "source_url": "https://www.fahasa.com/blindbox-do-choi-lap-rap-model-kit-moshow-version-1-sembo-900043.html",
    "label": null,
    "episode": null,
    "stock_status": "in_stock",
    "reviews_count": null,
    "rating_value": null,
    "category": "Đồ chơi - Lưu niệm"
  },
  {
    "source_id": "1053082",
    "title": "Blindbox Đồ Chơi Lắp Ráp Model Kit Iron Saga F6 - Version 1 - YK16 - Sembo 900040",
    "slug": "blindbox-do-choi-lap-rap-model-kit-iron-saga-f6-version-1-yk16-sembo-900040",
    "price": 54000,
    "original_price": 60000,
    "discount_percent": 10,
    "description_html": null,
    "image_url": "https://cdn1.fahasa.com/media/catalog/product/6/9/6941827014020.jpg",
    "source_url": "https://www.fahasa.com/blindbox-do-choi-lap-rap-model-kit-iron-saga-f6-version-1-yk16-sembo-900040.html",
    "label": null,
    "episode": null,
    "stock_status": "in_stock",
    "reviews_count": null,
    "rating_value": null,
    "category": "Đồ chơi - Lưu niệm"
  },
  {
    "source_id": "1053295",
    "title": "Đồ Chơi Lắp Ráp Bộ Chiến Đấu Chiến Giáp Rồng Của Lloyd - Lego Ninjago 71862 (81 Mảnh Ghép)",
    "slug": "do-choi-lap-rap-bo-chien-dau-chien-giap-rong-cua-lloyd-lego-ninjago-71862-81-manh-ghep",
    "price": 287100,
    "original_price": 319000,
    "discount_percent": 10,
    "description_html": null,
    "image_url": "https://cdn1.fahasa.com/media/catalog/product/5/7/5702018055700.jpg",
    "source_url": "https://www.fahasa.com/do-choi-lap-rap-bo-chien-dau-chien-giap-rong-cua-lloyd-lego-ninjago-71862-81-manh-ghep.html",
    "label": null,
    "episode": null,
    "stock_status": "in_stock",
    "reviews_count": null,
    "rating_value": null,
    "category": "Đồ chơi - Lưu niệm"
  },
  {
    "source_id": "255590",
    "title": "Siêu Xe Hot Wheels C4982 (Mẫu Màu Giao Ngẫu Nhiên)",
    "slug": "sieu-xe-hot-wheels-c4982-mau-mau-giao-ngau-nhien",
    "price": 62000,
    "original_price": 69000,
    "discount_percent": 10,
    "description_html": null,
    "image_url": "https://cdn1.fahasa.com/media/catalog/product/h/o/hot-wheels-1.jpg",
    "source_url": "https://www.fahasa.com/sieu-xe-hot-wheels-c4982-mau-mau-giao-ngau-nhien.html",
    "label": null,
    "episode": null,
    "stock_status": "in_stock",
    "reviews_count": null,
    "rating_value": null,
    "category": "Đồ chơi - Lưu niệm"
  },
  {
    "source_id": "1058310",
    "title": "Bộ Thẻ Sưu Tập - Card Collection Thám Tử Lừng Danh Conan - Thiên Thần Sa Ngã Trên Xa Lộ - Character In Photo (5 Cards Ngẫu Nhiên/Túi)",
    "slug": "bo-the-suu-tap-card-collection-tham-tu-lung-danh-conan-thien-than-sa-nga-tren-xa-lo-character-in-photo-5-cards-ngau-nhien-tui",
    "price": 69000,
    "original_price": 69000,
    "discount_percent": 0,
    "description_html": null,
    "image_url": "https://cdn1.fahasa.com/media/catalog/product/8/9/8936130672096.jpg",
    "source_url": "https://www.fahasa.com/bo-the-suu-tap-card-collection-tham-tu-lung-danh-conan-thien-than-sa-nga-tren-xa-lo-character-in-photo-5-cards-ngau-nhien-tui.html",
    "label": null,
    "episode": null,
    "stock_status": "in_stock",
    "reviews_count": null,
    "rating_value": null,
    "category": "Đồ chơi - Lưu niệm"
  },
  {
    "source_id": "1047706",
    "title": "Đồ Chơi Blindbox Lắp Ráp Mô Hình Transformers - Defender Version DV07 - Power Of The Beast - Blokees ET62",
    "slug": "do-choi-blindbox-lap-rap-mo-hinh-transformers-defender-version-dv07-power-of-the-beast-blokees-et62",
    "price": 44000,
    "original_price": 49000,
    "discount_percent": 10,
    "description_html": null,
    "image_url": "https://cdn1.fahasa.com/media/catalog/product/8/9/8935339421535.jpg",
    "source_url": "https://www.fahasa.com/do-choi-blindbox-lap-rap-mo-hinh-transformers-defender-version-dv07-power-of-the-beast-blokees-et62.html",
    "label": null,
    "episode": null,
    "stock_status": "in_stock",
    "reviews_count": null,
    "rating_value": null,
    "category": "Đồ chơi - Lưu niệm"
  },
  {
    "source_id": "1052999",
    "title": "Đồ Chơi Sưu Tầm Đám Cưới Quái Thú Fuggler Wedding Fuggs 9 Inch - Zuru Toys 15757",
    "slug": "do-choi-suu-tam-dam-cuoi-quai-thu-fuggler-wedding-fuggs-9-inch-zuru-toys-15757",
    "price": 891000,
    "original_price": 990000,
    "discount_percent": 10,
    "description_html": null,
    "image_url": "https://cdn1.fahasa.com/media/catalog/product/4/8/4894680049017.jpg",
    "source_url": "https://www.fahasa.com/do-choi-suu-tam-dam-cuoi-quai-thu-fuggler-wedding-fuggs-9-inch-zuru-toys-15757.html",
    "label": null,
    "episode": null,
    "stock_status": "in_stock",
    "reviews_count": null,
    "rating_value": null,
    "category": "Đồ chơi - Lưu niệm"
  },
  {
    "source_id": "1051476",
    "title": "Blindbox Đồ Chơi Lắp Ráp Mô Hình Khủng Long Jurassic World - Terraventure TS03 - Blokees EJ03",
    "slug": "blindbox-do-choi-lap-rap-mo-hinh-khung-long-jurassic-world-terraventure-ts03-blokees-ej03",
    "price": 62100,
    "original_price": 69000,
    "discount_percent": 10,
    "description_html": null,
    "image_url": "https://cdn1.fahasa.com/media/catalog/product/8/9/8935339423102.jpg",
    "source_url": "https://www.fahasa.com/blindbox-do-choi-lap-rap-mo-hinh-khung-long-jurassic-world-terraventure-ts03-blokees-ej03.html",
    "label": null,
    "episode": null,
    "stock_status": "in_stock",
    "reviews_count": null,
    "rating_value": null,
    "category": "Đồ chơi - Lưu niệm"
  },
  {
    "source_id": "1040977",
    "title": "Đồ Chơi Lắp Ráp Kai's Dragon Mech Battle Pack - Lego Ninjago 71851 (85 Mảnh Ghép)",
    "slug": "do-choi-lap-rap-kai-s-dragon-mech-battle-pack-lego-ninjago-71851-85-manh-ghep",
    "price": 279650,
    "original_price": 329000,
    "discount_percent": 15,
    "description_html": null,
    "image_url": "https://cdn1.fahasa.com/media/catalog/product/5/7/5702018031971.jpg",
    "source_url": "https://www.fahasa.com/do-choi-lap-rap-kai-s-dragon-mech-battle-pack-lego-ninjago-71851-85-manh-ghep.html",
    "label": null,
    "episode": null,
    "stock_status": "in_stock",
    "reviews_count": null,
    "rating_value": null,
    "category": "Đồ chơi - Lưu niệm"
  },
  {
    "source_id": "1058078",
    "title": "Bộ Tranh Tương Tác DIY Cô Tiên Xanh - Đi Đà Lạt",
    "slug": "bo-tranh-tuong-tac-diy-co-tien-xanh-di-da-lat",
    "price": 53100,
    "original_price": 59000,
    "discount_percent": 10,
    "description_html": null,
    "image_url": "https://cdn1.fahasa.com/media/catalog/product/3/9/3900000372770.jpg",
    "source_url": "https://www.fahasa.com/co-tien-xanh-quyen-tranh-di-da-lat.html",
    "label": null,
    "episode": null,
    "stock_status": "in_stock",
    "reviews_count": null,
    "rating_value": null,
    "category": "Đồ chơi - Lưu niệm"
  },
  {
    "source_id": "1052998",
    "title": "Đồ Chơi Sưu Tầm Quái Thú Cá Mập Fuggler Jaws 9 Inch - Zuru Toys 15747",
    "slug": "do-choi-suu-tam-quai-thu-ca-map-fuggler-jaws-9-inch-zuru-toys-15747",
    "price": 512100,
    "original_price": 569000,
    "discount_percent": 10,
    "description_html": null,
    "image_url": "https://cdn1.fahasa.com/media/catalog/product/4/8/4894680047846.jpg",
    "source_url": "https://www.fahasa.com/do-choi-suu-tam-quai-thu-ca-map-fuggler-jaws-9-inch-zuru-toys-15747.html",
    "label": null,
    "episode": null,
    "stock_status": "in_stock",
    "reviews_count": null,
    "rating_value": null,
    "category": "Đồ chơi - Lưu niệm"
  },
  {
    "source_id": "281477",
    "title": "Lớp Học Mật Ngữ - Siêu Thú Ngân Hà",
    "slug": "lop-hoc-mat-ngu-sieu-thu-ngan-ha",
    "price": 749000,
    "original_price": 749000,
    "discount_percent": 0,
    "description_html": null,
    "image_url": "https://cdn1.fahasa.com/media/catalog/product/8/9/8936130670702.jpg",
    "source_url": "https://www.fahasa.com/lop-hoc-mat-ngu-sieu-thu-ngan-ha.html",
    "label": null,
    "episode": null,
    "stock_status": "in_stock",
    "reviews_count": null,
    "rating_value": null,
    "category": "Đồ chơi - Lưu niệm"
  },
  {
    "source_id": "642600",
    "title": "Bộ Tranh Tương Tác Cô Tiên Xanh - Chuyến Đi Du Lịch",
    "slug": "bo-tranh-tuong-tac-co-tien-xanh-chuyen-di-du-lich",
    "price": 67500,
    "original_price": 75000,
    "discount_percent": 10,
    "description_html": null,
    "image_url": "https://cdn1.fahasa.com/media/catalog/product/3/9/3900000314343.jpg",
    "source_url": "https://www.fahasa.com/bo-tranh-tuong-tac-co-tien-xanh-chuyen-di-du-lich.html",
    "label": null,
    "episode": null,
    "stock_status": "in_stock",
    "reviews_count": null,
    "rating_value": null,
    "category": "Đồ chơi - Lưu niệm"
  },
  {
    "source_id": "583745",
    "title": "Sách Tương Tác  Khu Phố Tui Kèm Hộp Mù + Móc Khoá - Cô Tiên Xanh",
    "slug": "sach-tuong-tac-khu-pho-tui-kem-hop-mu-moc-khoa-co-tien-xanh",
    "price": 80000,
    "original_price": 89000,
    "discount_percent": 10,
    "description_html": null,
    "image_url": "https://cdn1.fahasa.com/media/catalog/product/3/9/3900000262569.jpg",
    "source_url": "https://www.fahasa.com/sach-tuong-tac-khu-pho-tui-kem-hop-mu-moc-khoa-co-tien-xanh.html",
    "label": null,
    "episode": null,
    "stock_status": "in_stock",
    "reviews_count": null,
    "rating_value": null,
    "category": "Đồ chơi - Lưu niệm"
  },
  {
    "source_id": "1037158",
    "title": "Đồ Chơi Lắp Ráp Mô Hình Jurassic World - Blokees 75642 - Terraventure",
    "slug": "do-choi-lap-rap-mo-hinh-jurassic-world-blokees-75642-terraventure",
    "price": 62000,
    "original_price": 69000,
    "discount_percent": 10,
    "description_html": null,
    "image_url": "https://cdn1.fahasa.com/media/catalog/product/8/9/8935339418917_1.jpg",
    "source_url": "https://www.fahasa.com/blokees-mo-hinh-jurassic-world-terraventure-ej02.html",
    "label": null,
    "episode": null,
    "stock_status": "in_stock",
    "reviews_count": null,
    "rating_value": null,
    "category": "Đồ chơi - Lưu niệm"
  },
  {
    "source_id": "1053316",
    "title": "Đồ Chơi Lắp Ráp Model Kit Moshow - Nhân Vật Takade Shingen, Date Masamune, Lancelot Of The Lake, Wu Chenghou - Phiên Bản Giới Hạn - Sembo 900047",
    "slug": "do-choi-lap-rap-model-kit-moshow-nhan-vat-takade-shingen-date-masamune-lancelot-of-the-lake-wu-chenghou-phien-ban-gioi-han-sembo-900047",
    "price": 792000,
    "original_price": 880000,
    "discount_percent": 10,
    "description_html": null,
    "image_url": "https://cdn1.fahasa.com/media/catalog/product/6/9/6941827015041.jpg",
    "source_url": "https://www.fahasa.com/do-choi-lap-rap-model-kit-moshow-nhan-vat-takade-shingen-date-masamune-lancelot-of-the-lake-wu-chenghou-phien-ban-gioi-han-sembo-900047.html",
    "label": null,
    "episode": null,
    "stock_status": "in_stock",
    "reviews_count": null,
    "rating_value": null,
    "category": "Đồ chơi - Lưu niệm"
  },
  {
    "source_id": "392364",
    "title": "Bộ Xếp Hình Khổ A4 Puzzle Minh Châu 35-02 - Thám Hiểm Đại Dương (35 Mảnh Ghép)",
    "slug": "bo-xep-hinh-kho-a4-puzzle-minh-chau-35-02-tham-hiem-dai-duong-35-manh-ghep",
    "price": 20500,
    "original_price": 23000,
    "discount_percent": 10,
    "description_html": null,
    "image_url": "https://cdn1.fahasa.com/media/catalog/product/3/9/3900000036726.jpg",
    "source_url": "https://www.fahasa.com/bo-xep-hinh-kho-a4-puzzle-minh-chau-35-02-tham-hiem-dai-duong-35-manh-ghep.html",
    "label": null,
    "episode": null,
    "stock_status": "in_stock",
    "reviews_count": null,
    "rating_value": null,
    "category": "Đồ chơi - Lưu niệm"
  },
  {
    "source_id": "1035740",
    "title": "Card Bo Góc - Spongebob - Kabao BN01 (3 Card Ngẫu Nhiên/Túi)",
    "slug": "card-bo-goc-spongebob-kabao-bn01-3-card-ngau-nhien-tui",
    "price": 6500,
    "original_price": 7500,
    "discount_percent": 13,
    "description_html": null,
    "image_url": "https://cdn1.fahasa.com/media/catalog/product/8/9/8935339417972.jpg",
    "source_url": "https://www.fahasa.com/card-bo-goc-spongebob-kabao-bn01.html",
    "label": null,
    "episode": null,
    "stock_status": "in_stock",
    "reviews_count": null,
    "rating_value": null,
    "category": "Đồ chơi - Lưu niệm"
  },
  {
    "source_id": "1042041",
    "title": "Thú Bông Ma Thuật - Magic Jellykins 6072461 (Sản Phẩm Bên Trong Giao Ngẫu Nhiên)",
    "slug": "thu-bong-ma-thuat-magic-jellykins-6072461-san-pham-ben-trong-giao-ngau-nhien",
    "price": 323000,
    "original_price": 359000,
    "discount_percent": 10,
    "description_html": null,
    "image_url": "https://cdn1.fahasa.com/media/catalog/product/8/9/8935337544342.jpg",
    "source_url": "https://www.fahasa.com/thu-bong-ma-thuat-magic-jellykins-6072461-san-pham-ben-trong-giao-ngau-nhien.html",
    "label": null,
    "episode": null,
    "stock_status": "in_stock",
    "reviews_count": null,
    "rating_value": null,
    "category": "Đồ chơi - Lưu niệm"
  },
  {
    "source_id": "1049487",
    "title": "Gối Bông Nhân Vật Doraemon - Phiên Bản Movie 2026 - 33 cm - Die Cut",
    "slug": "goi-bong-nhan-vat-doraemon-phien-ban-movie-2026-33-cm-die-cut",
    "price": 279000,
    "original_price": 310000,
    "discount_percent": 10,
    "description_html": null,
    "image_url": "https://cdn1.fahasa.com/media/catalog/product/8/9/8936235570464.jpg",
    "source_url": "https://www.fahasa.com/goi-bong-nhan-vat-doraemon-phim-2026-die-cut-33cm.html",
    "label": null,
    "episode": null,
    "stock_status": "in_stock",
    "reviews_count": null,
    "rating_value": null,
    "category": "Đồ chơi - Lưu niệm"
  },
  {
    "source_id": "641335",
    "title": "Đồ Chơi Lắp Ráp Mô Hình Transformers - DV02 - The Overthrow - Blokees 71302 (Mẫu Sản Phẩm Bên Trong Là Ngẫu Nhiên)",
    "slug": "do-choi-lap-rap-mo-hinh-transformers-dv02-the-overthrow-blokees-71302-mau-san-pham-ben-trong-la-ngau-nhien",
    "price": 44000,
    "original_price": 49000,
    "discount_percent": 10,
    "description_html": null,
    "image_url": "https://cdn1.fahasa.com/media/catalog/product/8/9/8935339410102.jpg",
    "source_url": "https://www.fahasa.com/blokees-mo-hinh-transformers-dv02-the-overthrow-et29-12-hop-khay.html",
    "label": null,
    "episode": null,
    "stock_status": "in_stock",
    "reviews_count": null,
    "rating_value": null,
    "category": "Đồ chơi - Lưu niệm"
  },
  {
    "source_id": "1040982",
    "title": "Đồ Chơi Lắp Ráp Ninja Character Display 15th Anniversary - Lego Ninjago 71866 (447 Mảnh Ghép)",
    "slug": "do-choi-lap-rap-ninja-character-display-15th-anniversary-lego-ninjago-71866-447-manh-ghep",
    "price": 1115000,
    "original_price": 1239000,
    "discount_percent": 10,
    "description_html": null,
    "image_url": "https://cdn1.fahasa.com/media/catalog/product/5/7/5702018055748.jpg",
    "source_url": "https://www.fahasa.com/do-choi-lap-rap-ninja-character-display-15th-anniversary-lego-ninjago-71866-447-manh-ghep.html",
    "label": null,
    "episode": null,
    "stock_status": "in_stock",
    "reviews_count": null,
    "rating_value": null,
    "category": "Đồ chơi - Lưu niệm"
  },
  {
    "source_id": "613641",
    "title": "Đồ Chơi Lắp Ráp Model Kit Nhân Vật Ngẫu Nhiên 9 Trong 1 - Sembo 900020",
    "slug": "do-choi-lap-rap-model-kit-nhan-vat-ngau-nhien-9-trong-1-sembo-900020",
    "price": 126000,
    "original_price": 140000,
    "discount_percent": 10,
    "description_html": null,
    "image_url": "https://cdn1.fahasa.com/media/catalog/product/6/9/6941827011630.jpg",
    "source_url": "https://www.fahasa.com/do-choi-lap-rap-model-kit-nhan-vat-ngau-nhien-9-trong-1-sembo-900020.html",
    "label": null,
    "episode": null,
    "stock_status": "in_stock",
    "reviews_count": null,
    "rating_value": null,
    "category": "Đồ chơi - Lưu niệm"
  },
  {
    "source_id": "705071",
    "title": "Mô Hình Kỷ Niệm 45 Năm Phim Điện Ảnh Doraemon (Mẫu Sản Phẩm Giao Ngẫu Nhiên)",
    "slug": "mo-hinh-ky-niem-45-nam-phim-dien-anh-doraemon-mau-san-pham-giao-ngau-nhien",
    "price": 165000,
    "original_price": 165000,
    "discount_percent": 0,
    "description_html": null,
    "image_url": "https://cdn1.fahasa.com/media/catalog/product/l/e/le.jpg",
    "source_url": "https://www.fahasa.com/mo-hinh-ky-niem-45-nam-phim-dien-anh-doraemon.html",
    "label": null,
    "episode": null,
    "stock_status": "in_stock",
    "reviews_count": null,
    "rating_value": null,
    "category": "Đồ chơi - Lưu niệm"
  },
  {
    "source_id": "1058307",
    "title": "Bộ Tranh Tương Tác Cô Tiên Xanh - Bánh Gấu Khéo Tay",
    "slug": "bo-tranh-tuong-tac-co-tien-xanh-banh-gau-kheo-tay",
    "price": 100800,
    "original_price": 112000,
    "discount_percent": 10,
    "description_html": null,
    "image_url": "https://cdn1.fahasa.com/media/catalog/product/3/9/3900000371568.jpg",
    "source_url": "https://www.fahasa.com/bo-tranh-tuong-tac-co-tien-xanh-banh-gau-kheo-tay.html",
    "label": null,
    "episode": null,
    "stock_status": "in_stock",
    "reviews_count": null,
    "rating_value": null,
    "category": "Đồ chơi - Lưu niệm"
  },
  {
    "source_id": "1058308",
    "title": "Bộ Tranh Tương Tác DIY Cô Tiên Xanh - Alô Đi Biển",
    "slug": "bo-tranh-tuong-tac-diy-co-tien-xanh-alo-di-bien",
    "price": 53100,
    "original_price": 59000,
    "discount_percent": 10,
    "description_html": null,
    "image_url": "https://cdn1.fahasa.com/media/catalog/product/3/9/3900000372787.jpg",
    "source_url": "https://www.fahasa.com/bo-tranh-tuong-tac-diy-co-tien-xanh-alo-di-bien.html",
    "label": null,
    "episode": null,
    "stock_status": "in_stock",
    "reviews_count": null,
    "rating_value": null,
    "category": "Đồ chơi - Lưu niệm"
  },
  {
    "source_id": "1037160",
    "title": "Đồ Chơi Blindbox Lắp Ráp Mô Hình Transformers - Defender Version 06 - Brutal Fang - Blokees ET56",
    "slug": "do-choi-blindbox-lap-rap-mo-hinh-transformers-defender-version-06-brutal-fang-blokees-et56",
    "price": 44000,
    "original_price": 49000,
    "discount_percent": 10,
    "description_html": null,
    "image_url": "https://cdn1.fahasa.com/media/catalog/product/8/9/8935339420125_1.jpg",
    "source_url": "https://www.fahasa.com/blokees-mo-hinh-transformers-defender-version-06-brutal-fang-et56.html",
    "label": null,
    "episode": null,
    "stock_status": "in_stock",
    "reviews_count": null,
    "rating_value": null,
    "category": "Đồ chơi - Lưu niệm"
  },
  {
    "source_id": "1033398",
    "title": "Blindbox Mô Hình Trang Trí Mini - Sonny Angel - Snack Series - Smiski",
    "slug": "blindbox-mo-hinh-trang-tri-mini-sonny-angel-snack-series-smiski",
    "price": 225000,
    "original_price": 225000,
    "discount_percent": 0,
    "description_html": null,
    "image_url": "https://cdn1.fahasa.com/media/catalog/product/6/9/6973374353970.jpg",
    "source_url": "https://www.fahasa.com/go-go-sonny-angel-snack-series.html",
    "label": null,
    "episode": null,
    "stock_status": "in_stock",
    "reviews_count": null,
    "rating_value": null,
    "category": "Đồ chơi - Lưu niệm"
  },
  {
    "source_id": "1053038",
    "title": "Đồ Chơi Sưu Tầm Quái Ú Khổng Lồ Fuggler Bigg Chunky Fuggs 18 Inch - Zuru Toys 15797 - Màu Xám",
    "slug": "do-choi-suu-tam-quai-u-khong-lo-fuggler-bigg-chunky-fuggs-18-inch-zuru-toys-15797-mau-xam",
    "price": 891000,
    "original_price": 990000,
    "discount_percent": 10,
    "description_html": null,
    "image_url": "https://cdn1.fahasa.com/media/catalog/product/4/8/4894680058439-mau6.jpg",
    "source_url": "https://www.fahasa.com/do-choi-suu-tam-quai-u-khong-lo-fuggler-bigg-chunky-fuggs-18-inch-zuru-toys-15797-mau-xam.html",
    "label": null,
    "episode": null,
    "stock_status": "in_stock",
    "reviews_count": null,
    "rating_value": null,
    "category": "Đồ chơi - Lưu niệm"
  },
  {
    "source_id": "392361",
    "title": "Bộ Xếp Hình Khổ A4 Puzzle Minh Châu 35-011 - Khu Rừng Vui Vẻ (35 Mảnh Ghép)",
    "slug": "bo-xep-hinh-kho-a4-puzzle-minh-chau-35-011-khu-rung-vui-ve-35-manh-ghep",
    "price": 20500,
    "original_price": 23000,
    "discount_percent": 10,
    "description_html": null,
    "image_url": "https://cdn1.fahasa.com/media/catalog/product/3/9/3900000036931.jpg",
    "source_url": "https://www.fahasa.com/bo-xep-hinh-kho-a4-puzzle-minh-chau-35-011-khu-rung-vui-ve-35-manh-ghep.html",
    "label": null,
    "episode": null,
    "stock_status": "in_stock",
    "reviews_count": null,
    "rating_value": null,
    "category": "Đồ chơi - Lưu niệm"
  },
  {
    "source_id": "765748",
    "title": "Đồ Chơi Lắp Ráp 12 Con Giáp - Starmerry 6563 (SM198B) - Rabbit (18 Mảnh Ghép)",
    "slug": "do-choi-lap-rap-12-con-giap-starmerry-6563-sm198b-rabbit-18-manh-ghep",
    "price": 14000,
    "original_price": 16000,
    "discount_percent": 12,
    "description_html": null,
    "image_url": "https://cdn1.fahasa.com/media/catalog/product/8/9/8935311516563-mau4.jpg",
    "source_url": "https://www.fahasa.com/do-choi-lap-rap-12-con-giap-starmerry-6563-sm198b-rabbit-18-manh-ghep.html",
    "label": null,
    "episode": null,
    "stock_status": "in_stock",
    "reviews_count": null,
    "rating_value": null,
    "category": "Đồ chơi - Lưu niệm"
  },
  {
    "source_id": "1052991",
    "title": "Đồ Chơi Sưu Tầm Fuggler Spongebob Keyrings 5 Inch - Zuru Toy 15756 - Spongebob",
    "slug": "do-choi-suu-tam-fuggler-spongebob-keyrings-5-inch-zuru-toy-15756-spongebob",
    "price": 296100,
    "original_price": 329000,
    "discount_percent": 10,
    "description_html": null,
    "image_url": "https://cdn1.fahasa.com/media/catalog/product/4/8/4894680049048-mau2_1.jpg",
    "source_url": "https://www.fahasa.com/do-choi-suu-tam-fuggler-spongebob-keyrings-5-inch-zuru-toy-15756-spongebob-1052991.html",
    "label": null,
    "episode": null,
    "stock_status": "in_stock",
    "reviews_count": null,
    "rating_value": null,
    "category": "Đồ chơi - Lưu niệm"
  },
  {
    "source_id": "1033432",
    "title": "Đồ Chơi Lắp Ráp Mô Hình Transformers - Wheels - Blokees 75604 (Mẫu Sản Phẩm Bên Trong Là Ngẫu Nhiên)",
    "slug": "do-choi-lap-rap-mo-hinh-transformers-wheels-blokees-75604-mau-san-pham-ben-trong-la-ngau-nhien",
    "price": 71000,
    "original_price": 79000,
    "discount_percent": 10,
    "description_html": null,
    "image_url": "https://cdn1.fahasa.com/media/catalog/product/8/9/8935339417958.jpg",
    "source_url": "https://www.fahasa.com/blokees-mo-hinh-lap-rap-transformers-wheels-blokees-et46.html",
    "label": null,
    "episode": null,
    "stock_status": "in_stock",
    "reviews_count": null,
    "rating_value": null,
    "category": "Đồ chơi - Lưu niệm"
  },
  {
    "source_id": "1053003",
    "title": "Đồ Chơi Sưu Tầm Quái Thú Khổng Lồ Fuggler Bigg Fugg 18 Inch - Zuru Toys 15758 - Cá Xanh",
    "slug": "do-choi-suu-tam-quai-thu-khong-lo-fuggler-bigg-fugg-18-inch-zuru-toys-15758-ca-xanh",
    "price": 891000,
    "original_price": 990000,
    "discount_percent": 10,
    "description_html": null,
    "image_url": "https://cdn1.fahasa.com/media/catalog/product/4/8/4894680049055-mau3.jpg",
    "source_url": "https://www.fahasa.com/do-choi-suu-tam-quai-thu-khong-lo-fuggler-bigg-fugg-18-inch-zuru-toys-15758-ca-xanh.html",
    "label": null,
    "episode": null,
    "stock_status": "in_stock",
    "reviews_count": null,
    "rating_value": null,
    "category": "Đồ chơi - Lưu niệm"
  },
  {
    "source_id": "392375",
    "title": "Bộ Xếp Hình Khổ A4 Puzzle Minh Châu 35-06 - Bé Chơi Công Viên (35 Mảnh Ghép)",
    "slug": "bo-xep-hinh-kho-a4-puzzle-minh-chau-35-06-be-choi-cong-vien-35-manh-ghep",
    "price": 20500,
    "original_price": 23000,
    "discount_percent": 10,
    "description_html": null,
    "image_url": "https://cdn1.fahasa.com/media/catalog/product/3/9/3900000036887.jpg",
    "source_url": "https://www.fahasa.com/bo-xep-hinh-kho-a4-puzzle-minh-chau-35-06-be-choi-cong-vien-35-manh-ghep.html",
    "label": null,
    "episode": null,
    "stock_status": "in_stock",
    "reviews_count": null,
    "rating_value": null,
    "category": "Đồ chơi - Lưu niệm"
  },
  {
    "source_id": "1058305",
    "title": "Bộ Tranh Gập Mái Trường Thân Yêu - Cô Tiên Xanh",
    "slug": "bo-tranh-gap-mai-truong-than-yeu-co-tien-xanh",
    "price": 53100,
    "original_price": 59000,
    "discount_percent": 10,
    "description_html": null,
    "image_url": "https://cdn1.fahasa.com/media/catalog/product/3/9/3900000279031.jpg",
    "source_url": "https://www.fahasa.com/bo-tranh-gap-mai-truong-than-yeu-co-tien-xanh.html",
    "label": null,
    "episode": null,
    "stock_status": "in_stock",
    "reviews_count": null,
    "rating_value": null,
    "category": "Đồ chơi - Lưu niệm"
  },
  {
    "source_id": "1048108",
    "title": "Đồ Chơi Sưu Tầm Fuggler Baby Fuggs 3.5 Inch - Zuru Toys 15704 - Screech",
    "slug": "do-choi-suu-tam-fuggler-baby-fuggs-3-5-inch-zuru-toys-15704-screech",
    "price": 170000,
    "original_price": 189000,
    "discount_percent": 10,
    "description_html": null,
    "image_url": "https://cdn1.fahasa.com/media/catalog/product/4/8/4894680039841-mau1_1.jpg",
    "source_url": "https://www.fahasa.com/do-choi-suu-tam-fuggler-baby-fuggs-3-5-inch-zuru-toys-15704-screech-1048108.html",
    "label": null,
    "episode": null,
    "stock_status": "in_stock",
    "reviews_count": null,
    "rating_value": null,
    "category": "Đồ chơi - Lưu niệm"
  },
  {
    "source_id": "1049908",
    "title": "Blindbox Đồ Chơi Mô Hình Bob & Tim - Best Buddies Series Vinyl Plush Keychain - 52Toys",
    "slug": "blindbox-do-choi-mo-hinh-bob-tim-best-buddies-series-vinyl-plush-keychain-52toys",
    "price": 360000,
    "original_price": 400000,
    "discount_percent": 10,
    "description_html": null,
    "image_url": "https://cdn1.fahasa.com/media/catalog/product/6/9/6958985053525.jpg",
    "source_url": "https://www.fahasa.com/52toys-6958985053525-do-choi-tre-em-mo-hinh-bob-tim-best-buddies-series-vinyl-plush-keychain-96-hop-thung.html",
    "label": null,
    "episode": null,
    "stock_status": "in_stock",
    "reviews_count": null,
    "rating_value": null,
    "category": "Đồ chơi - Lưu niệm"
  },
  {
    "source_id": "1048114",
    "title": "Đồ Chơi Sưu Tầm Fuggler Baby Fuggs 3.5 Inch - Zuru Toys 15704 - Reek-O",
    "slug": "do-choi-suu-tam-fuggler-baby-fuggs-3-5-inch-zuru-toys-15704-reek-o",
    "price": 170000,
    "original_price": 189000,
    "discount_percent": 10,
    "description_html": null,
    "image_url": "https://cdn1.fahasa.com/media/catalog/product/4/8/4894680039841-mau6_2.jpg",
    "source_url": "https://www.fahasa.com/do-choi-suu-tam-fuggler-baby-fuggs-3-5-inch-zuru-toys-15704-reek-o-1048114.html",
    "label": null,
    "episode": null,
    "stock_status": "in_stock",
    "reviews_count": null,
    "rating_value": null,
    "category": "Đồ chơi - Lưu niệm"
  },
  {
    "source_id": "1048116",
    "title": "Đồ Chơi Sưu Tầm Fuggler Baby Fuggs 3.5 Inch - Zuru Toys 15704 - Hedge Grog",
    "slug": "do-choi-suu-tam-fuggler-baby-fuggs-3-5-inch-zuru-toys-15704-hedge-grog",
    "price": 170000,
    "original_price": 189000,
    "discount_percent": 10,
    "description_html": null,
    "image_url": "https://cdn1.fahasa.com/media/catalog/product/z/6/z6972535929027_13e0ddc688de6ee910e535d1a33f818d_2.jpg",
    "source_url": "https://www.fahasa.com/do-choi-suu-tam-fuggler-baby-fuggs-3-5-inch-zuru-toys-15704-hedge-grog-1048116.html",
    "label": null,
    "episode": null,
    "stock_status": "in_stock",
    "reviews_count": null,
    "rating_value": null,
    "category": "Đồ chơi - Lưu niệm"
  },
  {
    "source_id": "1053023",
    "title": "Đồ Chơi Sưu Tầm Bó Hoa Quái Thú Fuggler Bouquet Set - Zuru Toys 15780 - Hồng Xanh",
    "slug": "do-choi-suu-tam-bo-hoa-quai-thu-fuggler-bouquet-set-zuru-toys-15780-hong-xanh",
    "price": 891000,
    "original_price": 990000,
    "discount_percent": 10,
    "description_html": null,
    "image_url": "https://cdn1.fahasa.com/media/catalog/product/4/8/4894680058293-mau2.jpg",
    "source_url": "https://www.fahasa.com/do-choi-suu-tam-bo-hoa-quai-thu-fuggler-bouquet-set-zuru-toys-15780-hong-xanh.html",
    "label": null,
    "episode": null,
    "stock_status": "in_stock",
    "reviews_count": null,
    "rating_value": null,
    "category": "Đồ chơi - Lưu niệm"
  },
  {
    "source_id": "1053024",
    "title": "Đồ Chơi Sưu Tầm Bó Hoa Quái Thú Fuggler Bouquet Set - Zuru Toys 15780 - Hồng Đen",
    "slug": "do-choi-suu-tam-bo-hoa-quai-thu-fuggler-bouquet-set-zuru-toys-15780-hong-den",
    "price": 891000,
    "original_price": 990000,
    "discount_percent": 10,
    "description_html": null,
    "image_url": "https://cdn1.fahasa.com/media/catalog/product/4/8/4894680058293-mau3.jpg",
    "source_url": "https://www.fahasa.com/do-choi-suu-tam-bo-hoa-quai-thu-fuggler-bouquet-set-zuru-toys-15780-hong-den.html",
    "label": null,
    "episode": null,
    "stock_status": "in_stock",
    "reviews_count": null,
    "rating_value": null,
    "category": "Đồ chơi - Lưu niệm"
  },
  {
    "source_id": "1051542",
    "title": "Blindbox Đồ Chơi Lắp Ráp Mô Hình Siêu Xe Transformers - Wheels C03 - Blokees ET64",
    "slug": "blindbox-do-choi-lap-rap-mo-hinh-sieu-xe-transformers-wheels-c03-blokees-et64",
    "price": 71100,
    "original_price": 79000,
    "discount_percent": 10,
    "description_html": null,
    "image_url": "https://cdn1.fahasa.com/media/catalog/product/8/9/8935339423119.jpg",
    "source_url": "https://www.fahasa.com/blindbox-do-choi-lap-rap-mo-hinh-sieu-xe-transformers-wheels-c03-blokees-et64.html",
    "label": null,
    "episode": null,
    "stock_status": "in_stock",
    "reviews_count": null,
    "rating_value": null,
    "category": "Đồ chơi - Lưu niệm"
  },
  {
    "source_id": "1053026",
    "title": "Blindbox Đồ Chơi Sưu Tầm Fuggler Alley Cat Keyrings 5 Inch - Zuru Toys 15789",
    "slug": "blindbox-do-choi-suu-tam-fuggler-alley-cat-keyrings-5-inch-zuru-toys-15789",
    "price": 359100,
    "original_price": 399000,
    "discount_percent": 10,
    "description_html": null,
    "image_url": "https://cdn1.fahasa.com/media/catalog/product/4/8/4894680058354.jpg",
    "source_url": "https://www.fahasa.com/blindbox-do-choi-suu-tam-fuggler-alley-cat-keyrings-5-inch-zuru-toys-15789.html",
    "label": null,
    "episode": null,
    "stock_status": "in_stock",
    "reviews_count": null,
    "rating_value": null,
    "category": "Đồ chơi - Lưu niệm"
  },
  {
    "source_id": "689842",
    "title": "Đồ Chơi Mô Hình Hộp Mù Transformers - Defender Version 03 - Heavy Metal War - Blokees ET32 (Sản Phẩm Bên Trong Là Ngẫu Nhiên)",
    "slug": "do-choi-mo-hinh-hop-mu-transformers-defender-version-03-heavy-metal-war-blokees-et32-san-pham-ben-trong-la-ngau-nhien",
    "price": 44000,
    "original_price": 49000,
    "discount_percent": 10,
    "description_html": null,
    "image_url": "https://cdn1.fahasa.com/media/catalog/product/8/9/8935339411161.jpg",
    "source_url": "https://www.fahasa.com/blokees-mo-hinh-transformers-dv03-heavy-metal-war-blokees-et32.html",
    "label": null,
    "episode": null,
    "stock_status": "in_stock",
    "reviews_count": null,
    "rating_value": null,
    "category": "Đồ chơi - Lưu niệm"
  },
  {
    "source_id": "1052232",
    "title": "Đồ Chơi Lắp Ráp Mô Hình Infinite Warrior - Chiến Binh Lửa - Keepplay 66001",
    "slug": "do-choi-lap-rap-mo-hinh-infinite-warrior-chien-binh-lua-keepplay-66001",
    "price": 269100,
    "original_price": 299000,
    "discount_percent": 10,
    "description_html": null,
    "image_url": "https://cdn1.fahasa.com/media/catalog/product/6/9/6936798329068.jpg",
    "source_url": "https://www.fahasa.com/do-choi-lap-rap-mo-hinh-infinite-warrior-chien-binh-lua-keepplay-66001.html",
    "label": null,
    "episode": null,
    "stock_status": "in_stock",
    "reviews_count": null,
    "rating_value": null,
    "category": "Đồ chơi - Lưu niệm"
  },
  {
    "source_id": "1053582",
    "title": "Blindbox Đồ Chơi Lắp Ráp Mô Hình Ultraman - Ultraman Defender Version 01-Hero's Journey - EU24",
    "slug": "blindbox-do-choi-lap-rap-mo-hinh-ultraman-ultraman-defender-version-01-hero-s-journey-eu24",
    "price": 44100,
    "original_price": 49000,
    "discount_percent": 10,
    "description_html": null,
    "image_url": "https://cdn1.fahasa.com/media/catalog/product/8/9/8935339421573.jpg",
    "source_url": "https://www.fahasa.com/blindbox-do-choi-lap-rap-mo-hinh-ultraman-ultraman-defender-version-01-hero-s-journey-eu24.html",
    "label": null,
    "episode": null,
    "stock_status": "in_stock",
    "reviews_count": null,
    "rating_value": null,
    "category": "Đồ chơi - Lưu niệm"
  },
  {
    "source_id": "1053005",
    "title": "Đồ Chơi Sưu Tầm Quái Thú Khổng Lồ Fuggler Bigg Fugg 18 Inch - Zuru Toys 15758 - Lười Xám",
    "slug": "do-choi-suu-tam-quai-thu-khong-lo-fuggler-bigg-fugg-18-inch-zuru-toys-15758-luoi-xam",
    "price": 891000,
    "original_price": 990000,
    "discount_percent": 10,
    "description_html": null,
    "image_url": "https://cdn1.fahasa.com/media/catalog/product/4/8/4894680049055-mau5.jpg",
    "source_url": "https://www.fahasa.com/do-choi-suu-tam-quai-thu-khong-lo-fuggler-bigg-fugg-18-inch-zuru-toys-15758-luoi-xam.html",
    "label": null,
    "episode": null,
    "stock_status": "in_stock",
    "reviews_count": null,
    "rating_value": null,
    "category": "Đồ chơi - Lưu niệm"
  },
  {
    "source_id": "710699",
    "title": "Gấu Bông Kể Chuyện - Người Bạn Tâm Tình Của Bé - Màu Đỏ",
    "slug": "gau-bong-ke-chuyen-nguoi-ban-tam-tinh-cua-be-mau-do",
    "price": 899000,
    "original_price": 999000,
    "discount_percent": 10,
    "description_html": null,
    "image_url": "https://cdn1.fahasa.com/media/catalog/product/8/9/8935210312242.jpg",
    "source_url": "https://www.fahasa.com/gau-bong-ke-chuyen-nguoi-ban-tam-tinh-cua-be-mau-do.html",
    "label": null,
    "episode": null,
    "stock_status": "in_stock",
    "reviews_count": null,
    "rating_value": null,
    "category": "Đồ chơi - Lưu niệm"
  },
  {
    "source_id": "356906",
    "title": "Đồ Chơi Mô Hình Xe McLaren Senna SIKU 1537",
    "slug": "do-choi-mo-hinh-xe-mclaren-senna-siku-1537",
    "price": 116000,
    "original_price": 129000,
    "discount_percent": 10,
    "description_html": null,
    "image_url": "https://cdn1.fahasa.com/media/catalog/product/i/m/image_230300.jpg",
    "source_url": "https://www.fahasa.com/do-choi-mo-hinh-xe-mclaren-senna-siku-1537.html",
    "label": null,
    "episode": null,
    "stock_status": "in_stock",
    "reviews_count": null,
    "rating_value": null,
    "category": "Đồ chơi - Lưu niệm"
  },
  {
    "source_id": "671721",
    "title": "Đồ Chơi Hộp Mù Lắp Ráp Biệt Đội An Ninh Skidibi - Wangao 288031",
    "slug": "do-choi-hop-mu-lap-rap-biet-doi-an-ninh-skidibi-wangao-288031",
    "price": 22500,
    "original_price": 25000,
    "discount_percent": 10,
    "description_html": null,
    "image_url": "https://cdn1.fahasa.com/media/catalog/product/6/9/6975402701180.jpg",
    "source_url": "https://www.fahasa.com/do-choi-hop-mu-lap-rap-biet-doi-an-ninh-skidibi-wangao-288031.html",
    "label": null,
    "episode": null,
    "stock_status": "in_stock",
    "reviews_count": null,
    "rating_value": null,
    "category": "Đồ chơi - Lưu niệm"
  },
  {
    "source_id": "1057292",
    "title": "Đồ Chơi Sưu Tầm Quái Thú Nổi Loạn Fuggler Baddies Fuggs 9 Inch - Zuru Toys 15784 - Rabid Rabbit",
    "slug": "do-choi-suu-tam-quai-thu-noi-loan-fuggler-baddies-fuggs-9-inch-zuru-toys-15784-rabid-rabbit",
    "price": 512100,
    "original_price": 569000,
    "discount_percent": 10,
    "description_html": null,
    "image_url": "https://cdn1.fahasa.com/media/catalog/product/4/8/4894680058033-mau4.jpg",
    "source_url": "https://www.fahasa.com/do-choi-suu-tam-quai-thu-noi-loan-fuggler-baddies-fuggs-9-inch-zuru-toys-15784-rabid-rabbit.html",
    "label": null,
    "episode": null,
    "stock_status": "in_stock",
    "reviews_count": null,
    "rating_value": null,
    "category": "Đồ chơi - Lưu niệm"
  },
  {
    "source_id": "671722",
    "title": "Đồ Chơi Hộp Mù Lắp Ráp Lực Lượng Đặc Nhiệm - Wangao 588007",
    "slug": "do-choi-hop-mu-lap-rap-luc-luong-dac-nhiem-wangao-588007",
    "price": 22500,
    "original_price": 25000,
    "discount_percent": 10,
    "description_html": null,
    "image_url": "https://cdn1.fahasa.com/media/catalog/product/6/9/6975402701395.jpg",
    "source_url": "https://www.fahasa.com/do-choi-hop-mu-lap-rap-luc-luong-dac-nhiem-wangao-588007.html",
    "label": null,
    "episode": null,
    "stock_status": "in_stock",
    "reviews_count": null,
    "rating_value": null,
    "category": "Đồ chơi - Lưu niệm"
  },
  {
    "source_id": "1051155",
    "title": "Đồ Chơi Vòng Xoắn Thư Giãn - Gems - Tangle 2410 - Mẫu 2",
    "slug": "do-choi-vong-xoan-thu-gian-gems-tangle-2410-mau-2",
    "price": 134000,
    "original_price": 149000,
    "discount_percent": 10,
    "description_html": null,
    "image_url": "https://cdn1.fahasa.com/media/catalog/product/8/9/8935337547398-mau2.jpg",
    "source_url": "https://www.fahasa.com/do-choi-vong-xoan-thu-gian-gems-tangle-2410-mau-2.html",
    "label": null,
    "episode": null,
    "stock_status": "in_stock",
    "reviews_count": null,
    "rating_value": null,
    "category": "Đồ chơi - Lưu niệm"
  },
  {
    "source_id": "437064",
    "title": "Bột Nặn Clever Dough 56g  - Colokit MD-C008 - Màu Đỏ",
    "slug": "bot-nan-clever-dough-56g-colokit-md-c008-mau-do",
    "price": 14000,
    "original_price": 16000,
    "discount_percent": 12,
    "description_html": null,
    "image_url": "https://cdn1.fahasa.com/media/catalog/product/8/9/8935324008246.jpg",
    "source_url": "https://www.fahasa.com/bot-nan-md-c008-do-t96.html",
    "label": null,
    "episode": null,
    "stock_status": "in_stock",
    "reviews_count": null,
    "rating_value": null,
    "category": "Đồ chơi - Lưu niệm"
  },
  {
    "source_id": "765747",
    "title": "Đồ Chơi Lắp Ráp 12 Con Giáp - Starmerry 6563 (SM198B) - Tiger (23 Mảnh Ghép)",
    "slug": "do-choi-lap-rap-12-con-giap-starmerry-6563-sm198b-tiger-23-manh-ghep",
    "price": 14000,
    "original_price": 16000,
    "discount_percent": 12,
    "description_html": null,
    "image_url": "https://cdn1.fahasa.com/media/catalog/product/8/9/8935311516563-mau3.jpg",
    "source_url": "https://www.fahasa.com/do-choi-lap-rap-12-con-giap-starmerry-6563-sm198b-tiger-23-manh-ghep.html",
    "label": null,
    "episode": null,
    "stock_status": "in_stock",
    "reviews_count": null,
    "rating_value": null,
    "category": "Đồ chơi - Lưu niệm"
  },
  {
    "source_id": "1050511",
    "title": "Đồ Chơi Lắp Ráp Mô Hình Siêu Xe Transformers - Wheels C02 - Blokees ET60",
    "slug": "do-choi-lap-rap-mo-hinh-sieu-xe-transformers-wheels-c02-blokees-et60",
    "price": 71000,
    "original_price": 79000,
    "discount_percent": 10,
    "description_html": null,
    "image_url": "https://cdn1.fahasa.com/media/catalog/product/8/9/8935339421337.jpg",
    "source_url": "https://www.fahasa.com/blokees-mo-hinh-lap-rap-transformers-wheels-c02-blokees-et60.html",
    "label": null,
    "episode": null,
    "stock_status": "in_stock",
    "reviews_count": null,
    "rating_value": null,
    "category": "Đồ chơi - Lưu niệm"
  },
  {
    "source_id": "1051156",
    "title": "Đồ Chơi Vòng Xoắn Thư Giãn - Gems - Tangle 2410 - Mẫu 3",
    "slug": "do-choi-vong-xoan-thu-gian-gems-tangle-2410-mau-3",
    "price": 134000,
    "original_price": 149000,
    "discount_percent": 10,
    "description_html": null,
    "image_url": "https://cdn1.fahasa.com/media/catalog/product/8/9/8935337547398-mau3.jpg",
    "source_url": "https://www.fahasa.com/do-choi-vong-xoan-thu-gian-gems-tangle-2410-mau-3.html",
    "label": null,
    "episode": null,
    "stock_status": "in_stock",
    "reviews_count": null,
    "rating_value": null,
    "category": "Đồ chơi - Lưu niệm"
  },
  {
    "source_id": "437079",
    "title": "Bột Nặn Clever Dough 56g  - Colokit MD-C008 - Màu Hồng",
    "slug": "bot-nan-clever-dough-56g-colokit-md-c008-mau-hong",
    "price": 14000,
    "original_price": 16000,
    "discount_percent": 12,
    "description_html": null,
    "image_url": "https://cdn1.fahasa.com/media/catalog/product/8/9/8935324008215.jpg",
    "source_url": "https://www.fahasa.com/bot-nan-clever-dough-56g-colokit-md-c008-mau-hong.html",
    "label": null,
    "episode": null,
    "stock_status": "in_stock",
    "reviews_count": null,
    "rating_value": null,
    "category": "Đồ chơi - Lưu niệm"
  },
  {
    "source_id": "1033429",
    "title": "Hộp Mù Lắp Ráp Mô Hình Minions Mokoo - 03 Belloween - Blokees 75663",
    "slug": "hop-mu-lap-rap-mo-hinh-minions-mokoo-03-belloween-blokees-75663",
    "price": 161000,
    "original_price": 179000,
    "discount_percent": 10,
    "description_html": null,
    "image_url": "https://cdn1.fahasa.com/media/catalog/product/8/9/8935339417927.jpg",
    "source_url": "https://www.fahasa.com/blokees-mo-hinh-trang-tri-minions-mokoo-03-belloween-blokees-ed11.html",
    "label": null,
    "episode": null,
    "stock_status": "in_stock",
    "reviews_count": null,
    "rating_value": null,
    "category": "Đồ chơi - Lưu niệm"
  },
  {
    "source_id": "998885",
    "title": "Đồ Chơi Lắp Ráp Thế Giới Khủng Long - Dr.Star 1043A (83 Mảnh Ghép) - Brachiosaurus",
    "slug": "do-choi-lap-rap-the-gioi-khung-long-dr-star-1043a-83-manh-ghep-brachiosaurus",
    "price": 45500,
    "original_price": 51000,
    "discount_percent": 10,
    "description_html": null,
    "image_url": "https://cdn1.fahasa.com/media/catalog/product/8/9/8935311517409-mau2.jpg",
    "source_url": "https://www.fahasa.com/do-choi-lap-rap-the-gioi-khung-long-dr-star-1043a-83-manh-ghep-brachiosaurus.html",
    "label": null,
    "episode": null,
    "stock_status": "in_stock",
    "reviews_count": null,
    "rating_value": null,
    "category": "Đồ chơi - Lưu niệm"
  },
  {
    "source_id": "765753",
    "title": "Đồ Chơi Lắp Ráp 12 Con Giáp - Starmerry 6563 (SM198B) - Monkey (18 Mảnh Ghép)",
    "slug": "do-choi-lap-rap-12-con-giap-starmerry-6563-sm198b-monkey-18-manh-ghep",
    "price": 14000,
    "original_price": 16000,
    "discount_percent": 12,
    "description_html": null,
    "image_url": "https://cdn1.fahasa.com/media/catalog/product/8/9/8935311516563-mau9.jpg",
    "source_url": "https://www.fahasa.com/do-choi-lap-rap-12-con-giap-starmerry-6563-sm198b-monkey-18-manh-ghep.html",
    "label": null,
    "episode": null,
    "stock_status": "in_stock",
    "reviews_count": null,
    "rating_value": null,
    "category": "Đồ chơi - Lưu niệm"
  },
  {
    "source_id": "597466",
    "title": "Bộ Xếp Hình Puzzle Minh Châu 35-040 - Gia Đình Cánh Cụt (35 Mảnh Ghép)",
    "slug": "bo-xep-hinh-puzzle-minh-chau-35-040-gia-dinh-canh-cut-35-manh-ghep",
    "price": 20500,
    "original_price": 23000,
    "discount_percent": 10,
    "description_html": null,
    "image_url": "https://cdn1.fahasa.com/media/catalog/product/3/9/3900000273213-dd.jpg",
    "source_url": "https://www.fahasa.com/bo-xep-hinh-puzzle-minh-chau-35-040-gia-dinh-canh-cut-35-manh-ghep.html",
    "label": null,
    "episode": null,
    "stock_status": "in_stock",
    "reviews_count": null,
    "rating_value": null,
    "category": "Đồ chơi - Lưu niệm"
  },
  {
    "source_id": "437082",
    "title": "Bột Nặn Clever Dough 56g  - Colokit MD-C008 - Màu Vàng",
    "slug": "bot-nan-clever-dough-56g-colokit-md-c008-mau-vang",
    "price": 14000,
    "original_price": 16000,
    "discount_percent": 12,
    "description_html": null,
    "image_url": "https://cdn1.fahasa.com/media/catalog/product/8/9/8935324008260.jpg",
    "source_url": "https://www.fahasa.com/bot-nan-clever-dough-56g-colokit-md-c008-mau-vang.html",
    "label": null,
    "episode": null,
    "stock_status": "in_stock",
    "reviews_count": null,
    "rating_value": null,
    "category": "Đồ chơi - Lưu niệm"
  },
  {
    "source_id": "136569",
    "title": "Xe Lamborghini Aventador Lp 700-4 - 1449",
    "slug": "xe-lamborghini-aventador-lp-700-4-1449",
    "price": 116000,
    "original_price": 129000,
    "discount_percent": 10,
    "description_html": null,
    "image_url": "https://cdn1.fahasa.com/media/catalog/product/4/0/4006874014491.jpg",
    "source_url": "https://www.fahasa.com/xe-lamborghini-aventador-lp-700-4-1449.html",
    "label": null,
    "episode": null,
    "stock_status": "in_stock",
    "reviews_count": null,
    "rating_value": null,
    "category": "Đồ chơi - Lưu niệm"
  },
  {
    "source_id": "246691",
    "title": "Sáp Nặn 12M MC-016 - Hồng",
    "slug": "sap-nan-12m-mc-016-hong",
    "price": 32000,
    "original_price": 36000,
    "discount_percent": 11,
    "description_html": null,
    "image_url": "https://cdn1.fahasa.com/media/catalog/product/8/9/8935001847014-mau3.jpg",
    "source_url": "https://www.fahasa.com/sap-nan-12m-mc-016-hong.html",
    "label": null,
    "episode": null,
    "stock_status": "in_stock",
    "reviews_count": null,
    "rating_value": null,
    "category": "Đồ chơi - Lưu niệm"
  },
  {
    "source_id": "1053002",
    "title": "Đồ Chơi Sưu Tầm Quái Thú Khổng Lồ Fuggler Bigg Fugg 18 Inch - Zuru Toys 15758 - Màu Loang",
    "slug": "do-choi-suu-tam-quai-thu-khong-lo-fuggler-bigg-fugg-18-inch-zuru-toys-15758-mau-loang",
    "price": 891000,
    "original_price": 990000,
    "discount_percent": 10,
    "description_html": null,
    "image_url": "https://cdn1.fahasa.com/media/catalog/product/4/8/4894680049055-mau2.jpg",
    "source_url": "https://www.fahasa.com/do-choi-suu-tam-quai-thu-khong-lo-fuggler-bigg-fugg-18-inch-zuru-toys-15758-mau-loang.html",
    "label": null,
    "episode": null,
    "stock_status": "in_stock",
    "reviews_count": null,
    "rating_value": null,
    "category": "Đồ chơi - Lưu niệm"
  },
  {
    "source_id": "1034983",
    "title": "Đồ Chơi Lắp Ráp Nhân Vật Model Kit - Đại Chiến Tây Du - Sembo 900037 (Mẫu Sản Phẩm Ngẫu Nhiên)",
    "slug": "do-choi-lap-rap-nhan-vat-model-kit-dai-chien-tay-du-sembo-900037-mau-san-pham-ngau-nhien",
    "price": 99000,
    "original_price": 110000,
    "discount_percent": 10,
    "description_html": null,
    "image_url": "https://cdn1.fahasa.com/media/catalog/product/6/9/6941827013276.jpg",
    "source_url": "https://www.fahasa.com/do-choi-lap-rap-nhan-vat-model-kit-dai-chien-tay-du-sembo-900037-mau-san-pham-ngau-nhien.html",
    "label": null,
    "episode": null,
    "stock_status": "in_stock",
    "reviews_count": null,
    "rating_value": null,
    "category": "Đồ chơi - Lưu niệm"
  },
  {
    "source_id": "1051161",
    "title": "Đồ Chơi Vòng Xoắn Thư Giãn - Cloud - Tangle 2800 - Mẫu 2",
    "slug": "do-choi-vong-xoan-thu-gian-cloud-tangle-2800-mau-2",
    "price": 134000,
    "original_price": 149000,
    "discount_percent": 10,
    "description_html": null,
    "image_url": "https://cdn1.fahasa.com/media/catalog/product/8/9/8935337547381-mau2.jpg",
    "source_url": "https://www.fahasa.com/do-choi-vong-xoan-thu-gian-cloud-tangle-2800-mau-2.html",
    "label": null,
    "episode": null,
    "stock_status": "in_stock",
    "reviews_count": null,
    "rating_value": null,
    "category": "Đồ chơi - Lưu niệm"
  },
  {
    "source_id": "392372",
    "title": "Bộ Xếp Hình Khổ A4 Puzzle Minh Châu 35-03 - Bé Đi Picnic (35 Mảnh Ghép)",
    "slug": "bo-xep-hinh-kho-a4-puzzle-minh-chau-35-03-be-di-picnic-35-manh-ghep",
    "price": 20500,
    "original_price": 23000,
    "discount_percent": 10,
    "description_html": null,
    "image_url": "https://cdn1.fahasa.com/media/catalog/product/3/9/3900000036733.jpg",
    "source_url": "https://www.fahasa.com/bo-xep-hinh-kho-a4-puzzle-minh-chau-35-03-be-di-picnic-35-manh-ghep.html",
    "label": null,
    "episode": null,
    "stock_status": "in_stock",
    "reviews_count": null,
    "rating_value": null,
    "category": "Đồ chơi - Lưu niệm"
  },
  {
    "source_id": "1056155",
    "title": "Đồ Chơi Bóng Pokeball Với Pokemon 4 Biểu Cảm Series 2 - Pokemon Toys 8104 (Mẫu Sản Phẩm Bên Trong Là Ngẫu Nhiên)",
    "slug": "do-choi-bong-pokeball-voi-pokemon-4-bieu-cam-series-2-pokemon-toys-8104-mau-san-pham-ben-trong-la-ngau-nhien",
    "price": 98100,
    "original_price": 109000,
    "discount_percent": 10,
    "description_html": null,
    "image_url": "https://cdn1.fahasa.com/media/catalog/product/6/9/6951144481047.jpg",
    "source_url": "https://www.fahasa.com/do-choi-bong-pokeball-voi-pokemon-4-bieu-cam-series-2-pokemon-toys-8104-mau-san-pham-ben-trong-la-ngau-nhien.html",
    "label": null,
    "episode": null,
    "stock_status": "in_stock",
    "reviews_count": null,
    "rating_value": null,
    "category": "Đồ chơi - Lưu niệm"
  },
  {
    "source_id": "380352",
    "title": "Đồ Chơi Rubik 4 x 4 - Cresta DK81084",
    "slug": "do-choi-rubik-4-x-4-cresta-dk81084",
    "price": 75000,
    "original_price": 125000,
    "discount_percent": 40,
    "description_html": null,
    "image_url": "https://cdn1.fahasa.com/media/catalog/product/i/m/image_244718_1_3274.jpg",
    "source_url": "https://www.fahasa.com/do-choi-rubik-4-x-4-cresta-dk81084.html",
    "label": null,
    "episode": null,
    "stock_status": "in_stock",
    "reviews_count": null,
    "rating_value": null,
    "category": "Đồ chơi - Lưu niệm"
  },
  {
    "source_id": "1035743",
    "title": "Card Bo Góc - Crayon Shinchan - Fun Time 2 - Kabao BB20 (3 Card Ngẫu Nhiên/Túi)",
    "slug": "card-bo-goc-crayon-shinchan-fun-time-2-kabao-bb20-3-card-ngau-nhien-tui",
    "price": 12500,
    "original_price": 14000,
    "discount_percent": 10,
    "description_html": null,
    "image_url": "https://cdn1.fahasa.com/media/catalog/product/8/9/8935339418009.jpg",
    "source_url": "https://www.fahasa.com/card-bo-goc-crayon-shinchan-fun-time-2-kabao-bb20.html",
    "label": null,
    "episode": null,
    "stock_status": "in_stock",
    "reviews_count": null,
    "rating_value": null,
    "category": "Đồ chơi - Lưu niệm"
  },
  {
    "source_id": "725988",
    "title": "Đồ Chơi Mô Hình 12 Động Vật Hoang Dã CollectA -1 - CollectA A1105",
    "slug": "do-choi-mo-hinh-12-dong-vat-hoang-da-collecta-1-collecta-a1105",
    "price": 269000,
    "original_price": 299000,
    "discount_percent": 10,
    "description_html": null,
    "image_url": "https://cdn1.fahasa.com/media/catalog/product/4/8/4892900011059.jpg",
    "source_url": "https://www.fahasa.com/collecta-a1105-do-choi-tre-em-bo-suu-tap-mo-hinh-12-dong-vat-hoang-da-collecta-1-24-hop-thung.html",
    "label": null,
    "episode": null,
    "stock_status": "in_stock",
    "reviews_count": null,
    "rating_value": null,
    "category": "Đồ chơi - Lưu niệm"
  },
  {
    "source_id": "590363",
    "title": "Đồ Chơi Mô Hình Jujutsu Kaisen Acrylic Stand Kento Nanami - YuMe 11250-11255",
    "slug": "do-choi-mo-hinh-jujutsu-kaisen-acrylic-stand-kento-nanami-yume-11250-11255",
    "price": 107000,
    "original_price": 119000,
    "discount_percent": 10,
    "description_html": null,
    "image_url": "https://cdn1.fahasa.com/media/catalog/product/4/8/4895217512554.jpg",
    "source_url": "https://www.fahasa.com/md-jujutsu-kaisen-vat-pham-nhan-vat-trang-tri-jujutsu-kaisen-acrylic-stand-kento-nanami-24-cai-thung.html",
    "label": null,
    "episode": null,
    "stock_status": "in_stock",
    "reviews_count": null,
    "rating_value": null,
    "category": "Đồ chơi - Lưu niệm"
  },
  {
    "source_id": "262897",
    "title": "Lầy - Party Game Lầy Nhất Hệ Mặt Trời",
    "slug": "lay-party-game-lay-nhat-he-mat-troi",
    "price": 125000,
    "original_price": 139000,
    "discount_percent": 10,
    "description_html": null,
    "image_url": "https://cdn1.fahasa.com/media/catalog/product/8/9/8936130670658.jpg",
    "source_url": "https://www.fahasa.com/lay-party-game-lay-nhat-he-mat-troi.html",
    "label": null,
    "episode": null,
    "stock_status": "in_stock",
    "reviews_count": null,
    "rating_value": null,
    "category": "Đồ chơi - Lưu niệm"
  },
  {
    "source_id": "1057019",
    "title": "Đồ Chơi Búp Bê Thời Trang Game Dress To Impress - Bubble Gum Gal - PhatMojo FD4104",
    "slug": "do-choi-bup-be-thoi-trang-game-dress-to-impress-bubble-gum-gal-phatmojo-fd4104",
    "price": 809100,
    "original_price": 899000,
    "discount_percent": 10,
    "description_html": null,
    "image_url": "https://cdn1.fahasa.com/media/catalog/product/8/9/8935337552392.jpg",
    "source_url": "https://www.fahasa.com/do-choi-bup-be-thoi-trang-game-dress-to-impress-bubble-gum-gal-phatmojo-fd4104.html",
    "label": null,
    "episode": null,
    "stock_status": "in_stock",
    "reviews_count": null,
    "rating_value": null,
    "category": "Đồ chơi - Lưu niệm"
  },
  {
    "source_id": "1057022",
    "title": "Đồ Chơi Búp Bê Bí Ẩn Game Dress To Impress - V3 - PhatMojo MF4120",
    "slug": "do-choi-bup-be-bi-an-game-dress-to-impress-v3-phatmojo-mf4120",
    "price": 359100,
    "original_price": 399000,
    "discount_percent": 10,
    "description_html": null,
    "image_url": "https://cdn1.fahasa.com/media/catalog/product/8/9/8935337552354.jpg",
    "source_url": "https://www.fahasa.com/do-choi-bup-be-bi-an-game-dress-to-impress-v3-phatmojo-mf4120.html",
    "label": null,
    "episode": null,
    "stock_status": "in_stock",
    "reviews_count": null,
    "rating_value": null,
    "category": "Đồ chơi - Lưu niệm"
  },
  {
    "source_id": "1047875",
    "title": "Bộ Full Set Đồ Chơi Blindbox Lắp Ráp Mô Hình Transformers - Defender Version DV07 - Power Of The Beast - Blokees ET62 (12 Hộp)",
    "slug": "bo-full-set-do-choi-blindbox-lap-rap-mo-hinh-transformers-defender-version-dv07-power-of-the-beast-blokees-et62-12-hop",
    "price": 529200,
    "original_price": 588000,
    "discount_percent": 10,
    "description_html": null,
    "image_url": "https://cdn1.fahasa.com/media/catalog/product/3/9/3900000366038-0.jpg",
    "source_url": "https://www.fahasa.com/bo-full-set-do-choi-blindbox-lap-rap-mo-hinh-transformers-defender-version-dv07-power-of-the-beast-blokees-et62-12-hop.html",
    "label": null,
    "episode": null,
    "stock_status": "in_stock",
    "reviews_count": null,
    "rating_value": null,
    "category": "Đồ chơi - Lưu niệm"
  },
  {
    "source_id": "250460",
    "title": "Đồ Chơi Cờ Trí Tuệ UNO W2085",
    "slug": "do-choi-co-tri-tue-uno-w2085",
    "price": 152000,
    "original_price": 169000,
    "discount_percent": 10,
    "description_html": null,
    "image_url": "https://cdn1.fahasa.com/media/catalog/product/7/7/77e3eeaa6424151057b58254bcba52ca.jpg",
    "source_url": "https://www.fahasa.com/do-choi-co-tri-tue-uno-w2085.html",
    "label": null,
    "episode": null,
    "stock_status": "in_stock",
    "reviews_count": null,
    "rating_value": null,
    "category": "Đồ chơi - Lưu niệm"
  },
  {
    "source_id": "1049907",
    "title": "Blindbox Đồ Chơi Mô Hình Minion Monsters Series - 52Toys",
    "slug": "blindbox-do-choi-mo-hinh-minion-monsters-series-52toys",
    "price": 288000,
    "original_price": 320000,
    "discount_percent": 10,
    "description_html": null,
    "image_url": "https://cdn1.fahasa.com/media/catalog/product/6/9/6958985017657.jpg",
    "source_url": "https://www.fahasa.com/52toys-6958985017657-do-choi-tre-em-mo-hinh-minion-monsters-series-72-hop-thung.html",
    "label": null,
    "episode": null,
    "stock_status": "in_stock",
    "reviews_count": null,
    "rating_value": null,
    "category": "Đồ chơi - Lưu niệm"
  },
  {
    "source_id": "1048109",
    "title": "Đồ Chơi Sưu Tầm Fuggler Baby Fuggs 3.5 Inch - Zuru Toys 15704 - Mr Needles",
    "slug": "do-choi-suu-tam-fuggler-baby-fuggs-3-5-inch-zuru-toys-15704-mr-needles",
    "price": 170000,
    "original_price": 189000,
    "discount_percent": 10,
    "description_html": null,
    "image_url": "https://cdn1.fahasa.com/media/catalog/product/4/8/4894680039841-mau2_1.jpg",
    "source_url": "https://www.fahasa.com/do-choi-suu-tam-fuggler-baby-fuggs-3-5-inch-zuru-toys-15704-mr-needles-1048109.html",
    "label": null,
    "episode": null,
    "stock_status": "in_stock",
    "reviews_count": null,
    "rating_value": null,
    "category": "Đồ chơi - Lưu niệm"
  }
]